HTTP/1.1 200 OK
Cache-Control: private
Content-Type: application/soap+xml; charset=utf-8
Server: Microsoft-IIS/10.0
Set-Cookie: ASP.NET_SessionId=xu5mcvegxglg0zsdh3c5bb0y; path=/; HttpOnly; SameSite=Lax
X-AspNet-Version: 4.0.30319
X-Powered-By: ASP.NET
Date: Thu, 03 Sep 2020 18:41:30 GMT
Content-Length: 2335

<s:Envelope xmlns:s="http://www.w3.org/2003/05/soap-envelope" xmlns:a="http://www.w3.org/2005/08/addressing" xmlns:u="http://docs.oasis-open.org/wss/2004/01/oasis-200401-wss-wssecurity-utility-1.0.xsd"><s:Header><a:Action s:mustUnderstand="1">http://schemas.xmlsoap.org/ws/2005/02/trust/RSTR/SCT</a:Action><a:RelatesTo>urn:uuid:8b4abc84-12f9-420f-8231-e91ddb5d3197</a:RelatesTo><o:Security s:mustUnderstand="1" xmlns:o="http://docs.oasis-open.org/wss/2004/01/oasis-200401-wss-wssecurity-secext-1.0.xsd"><u:Timestamp u:Id="_0"><u:Created>2020-09-03T18:41:30.324Z</u:Created><u:Expires>2020-09-03T18:46:30.324Z</u:Expires></u:Timestamp></o:Security></s:Header><s:Body><t:RequestSecurityTokenResponse xmlns:t="http://schemas.xmlsoap.org/ws/2005/02/trust"><t:TokenType>http://schemas.xmlsoap.org/ws/2005/02/sc/sct</t:TokenType><t:RequestedSecurityToken><c:SecurityContextToken u:Id="uuid-7d5b50d7-faec-46d9-8cd1-df9bff49d02c-3387" xmlns:c="http://schemas.xmlsoap.org/ws/2005/02/sc"><c:Identifier>urn:uuid:28f8fe4f-3fc7-4ef8-a6f6-6244f6980f4f</c:Identifier></c:SecurityContextToken></t:RequestedSecurityToken><t:RequestedAttachedReference><o:SecurityTokenReference xmlns:o="http://docs.oasis-open.org/wss/2004/01/oasis-200401-wss-wssecurity-secext-1.0.xsd"><o:Reference ValueType="http://schemas.xmlsoap.org/ws/2005/02/sc/sct" URI="#uuid-7d5b50d7-faec-46d9-8cd1-df9bff49d02c-3387"></o:Reference></o:SecurityTokenReference></t:RequestedAttachedReference><t:RequestedUnattachedReference><o:SecurityTokenReference xmlns:o="http://docs.oasis-open.org/wss/2004/01/oasis-200401-wss-wssecurity-secext-1.0.xsd"><o:Reference URI="urn:uuid:28f8fe4f-3fc7-4ef8-a6f6-6244f6980f4f" ValueType="http://schemas.xmlsoap.org/ws/2005/02/sc/sct"></o:Reference></o:SecurityTokenReference></t:RequestedUnattachedReference><t:RequestedProofToken><t:ComputedKey>http://schemas.xmlsoap.org/ws/2005/02/trust/CK/PSHA1</t:ComputedKey></t:RequestedProofToken><t:Entropy><t:BinarySecret u:Id="uuid-7d5b50d7-faec-46d9-8cd1-df9bff49d02c-3388" Type="http://schemas.xmlsoap.org/ws/2005/02/trust/Nonce">ZE8gDikSrTN4VYMguEnJHP6ABph4Y24IRUSqcEsyduw=</t:BinarySecret></t:Entropy><t:Lifetime><u:Created>2020-09-03T18:41:30.324Z</u:Created><u:Expires>2020-09-04T09:41:30.324Z</u:Expires></t:Lifetime><t:KeySize>256</t:KeySize></t:RequestSecurityTokenResponse></s:Body></s:Envelope>